labels/__init__.py
labels/sheet.py
labels/specifications.py
pylabels-1.2.1.dist-info/DESCRIPTION.rst
pylabels-1.2.1.dist-info/METADATA
pylabels-1.2.1.dist-info/RECORD
pylabels-1.2.1.dist-info/WHEEL
pylabels-1.2.1.dist-info/metadata.json
pylabels-1.2.1.dist-info/top_level.txt
pylabels-1.2.1.dist-info/zip-safe
