Metadata-Version: 1.1
Name: pylabels
Version: 1.2.1
Summary: Library to generate PDFs for printing labels
Home-page: https://github.com/bcbnz/pylabels/
Author: Blair Bonnett
Author-email: blair.bonnett@gmail.com
License: GPLv3+
Platform: OS Independent
Classifier: Development Status :: 5 - Production/Stable
Classifier: License :: OSI Approved :: GNU General Public License v3 or later (GPLv3+)
Classifier: Operating System :: OS Independent
Classifier: Programming Language :: Python
Requires: reportlab
Provides: pylabels
